placeholder/__init__.py
placeholder/frontend/dist/index.html
placeholder/frontend/dist/assets/index.d8e9905b.js
placeholder/frontend/dist/assets/vendor.919a7b4c.js
sidemenu/__init__.py
sidemenu/frontend/dist/index.html
sidemenu/frontend/dist/assets/index.b6b9f3be.js
sidemenu/frontend/dist/assets/index.d0102e26.js
sidemenu/frontend/dist/assets/vendor.919a7b4c.js
streamlit_xui-0.0.2.dist-info/METADATA
streamlit_xui-0.0.2.dist-info/WHEEL
streamlit_xui-0.0.2.dist-info/top_level.txt
streamlit_xui-0.0.2.dist-info/RECORD
